repid/__init__.py
repid/_asyncify.py
repid/_processor.py
repid/_runner.py
repid/actor.py
repid/config.py
repid/connection.py
repid/converter.py
repid/health_check_server.py
repid/job.py
repid/logger.py
repid/main.py
repid/message.py
repid/py.typed
repid/queue.py
repid/retry_policy.py
repid/router.py
repid/serializer.py
repid/worker.py
repid/_utils/__init__.py
repid/_utils/args_bucket_in_message_id.py
repid/_utils/dataclass_hacks.py
repid/_utils/get_dependency.py
repid/_utils/internal_exceptions.py
repid/_utils/is_installed.py
repid/_utils/json_encoder.py
repid/_utils/regex_validators.py
repid/connections/__init__.py
repid/connections/abc.py
repid/connections/dummy/__init__.py
repid/connections/in_memory/__init__.py
repid/connections/in_memory/bucket_broker.py
repid/connections/in_memory/consumer.py
repid/connections/in_memory/message_broker.py
repid/connections/in_memory/utils.py
repid/connections/rabbitmq/__init__.py
repid/connections/rabbitmq/consumer.py
repid/connections/rabbitmq/message_broker.py
repid/connections/rabbitmq/protocols.py
repid/connections/rabbitmq/utils.py
repid/connections/redis/__init__.py
repid/connections/redis/bucket_broker.py
repid/connections/redis/consumer.py
repid/connections/redis/message_broker.py
repid/connections/redis/utils.py
repid/data/__init__.py
repid/data/_buckets.py
repid/data/_key.py
repid/data/_parameters.py
repid/data/priorities.py
repid/data/protocols.py
repid/dependencies/__init__.py
repid/dependencies/depends.py
repid/dependencies/message_dependency.py
repid/dependencies/protocols.py
repid/dependencies/resolver_context.py
repid/middlewares/__init__.py
repid/middlewares/consts.py
repid/middlewares/middleware.py
repid/middlewares/wrapper.py
repid/testing/__init__.py
repid/testing/modifiers.py
repid/testing/plugin.py
repid-1.6.0.dist-info/METADATA
repid-1.6.0.dist-info/WHEEL
repid-1.6.0.dist-info/entry_points.txt
repid-1.6.0.dist-info/licenses/LICENSE
repid-1.6.0.dist-info/RECORD
