Metadata-Version: 2.4
Name: repid
Version: 1.6.0
Summary: Repid framework: simple to use, fast to run and extensible to adopt job scheduler
Project-URL: documentation, https://repid.aleksul.space
Project-URL: funding, https://github.com/sponsors/aleksul
Project-URL: repository, https://github.com/aleksul/repid
Project-URL: tracker, https://github.com/aleksul/repid/issues
Author-email: aleksul <me@aleksul.space>
License: MIT
License-File: LICENSE
Classifier: Development Status :: 5 - Production/Stable
Classifier: License :: OSI Approved :: MIT License
Classifier: Programming Language :: Python :: 3
Classifier: Programming Language :: Python :: 3.10
Classifier: Programming Language :: Python :: 3.11
Classifier: Programming Language :: Python :: 3.12
Classifier: Programming Language :: Python :: 3.13
Classifier: Programming Language :: Python :: Implementation :: CPython
Classifier: Typing :: Typed
Requires-Python: >=3.10
Requires-Dist: packaging>=22.0
Requires-Dist: typing-extensions<5.0.0,>=4.3.0; python_version < '3.10'
Provides-Extra: amqp
Requires-Dist: aiormq<7.0.0,>=6.4.0; extra == 'amqp'
Provides-Extra: cron
Requires-Dist: croniter<6.0.0,>=2.0.0; extra == 'cron'
Provides-Extra: pydantic
Requires-Dist: pydantic<3.0.0,>=2.0.0; extra == 'pydantic'
Provides-Extra: redis
Requires-Dist: redis<6.0.0,>=5.0.0; extra == 'redis'
Provides-Extra: test
Requires-Dist: pytest; extra == 'test'
Requires-Dist: pytest-asyncio; extra == 'test'
